{
  "container_type": "Author",
  "filled": [
    "basics",
    "indices",
    "counts",
    "coauthors",
    "publications",
    "public_access"
  ],
  "scholar_id": "rMcTlDwAAAAJ",
  "source": "AUTHOR_PROFILE_PAGE",
  "name": "SRI ENDAH AGUSTINA",
  "url_picture": "https://scholar.googleusercontent.com/citations?view_op=view_photo&user=rMcTlDwAAAAJ&citpid=1",
  "affiliation": "Dept.of Mechanical & Biosystem Engineering, Faculty of Mechanical & Agricultural Technology- Bogor",
  "interests": [
    "renewable energy"
  ],
  "email_domain": "@apps.ipb.ac.id",
  "citedby": 201,
  "citedby5y": 144,
  "hindex": 6,
  "hindex5y": 5,
  "i10index": 5,
  "i10index5y": 3,
  "cites_per_year": {
    "2007": 1,
    "2008": 0,
    "2009": 1,
    "2010": 3,
    "2011": 3,
    "2012": 2,
    "2013": 0,
    "2014": 2,
    "2015": 6,
    "2016": 6,
    "2017": 12,
    "2018": 18,
    "2019": 21,
    "2020": 32,
    "2021": 22,
    "2022": 28,
    "2023": 30,
    "2024": 11
  },
  "coauthors": [],
  "publications": [
    {
      "container_type": "Publication",
      "source": "AUTHOR_PUBLICATION_ENTRY",
      "bib": {
        "title": "Analisa motor DC (Direct Current) sebagai penggerak mobil listrik",
        "pub_year": "2015",
        "citation": "vol 2, 28-34, 2015"
      },
      "filled": false,
      "author_pub_id": "rMcTlDwAAAAJ:dhFuZR0502QC",
      "num_citations": 108,
      "citedby_url": "https://scholar.google.com/scholar?oi=bibs&hl=en&cites=6864788720927263668",
      "cites_id": [
        "6864788720927263668"
      ]
    },
    {
      "container_type": "Publication",
      "source": "AUTHOR_PUBLICATION_ENTRY",
      "bib": {
        "title": "Prediksi kandungan kimia mangga arumanis selama penyimpanan dengan Spektroskopi NIR",
        "pub_year": "2015",
        "citation": "Jurnal Keteknikan Pertanian 3 (1), 2015"
      },
      "filled": false,
      "author_pub_id": "rMcTlDwAAAAJ:ZeXyd9-uunAC",
      "num_citations": 20,
      "citedby_url": "https://scholar.google.com/scholar?oi=bibs&hl=en&cites=7702348858380527432",
      "cites_id": [
        "7702348858380527432"
      ]
    },
    {
      "container_type": "Publication",
      "source": "AUTHOR_PUBLICATION_ENTRY",
      "bib": {
        "title": "Mesin Pengempa Briket Limbah Biomassa, Salah Satu Solusi Penyediaan Bahan Bakar Pengganti BBM untuk Rumah Tangga dan Industri Kecil",
        "pub_year": "2005",
        "citation": "Prosiding Seminar Nasional dan Kongres Perteta, Bandung, 2005"
      },
      "filled": false,
      "author_pub_id": "rMcTlDwAAAAJ:4DMP91E08xMC",
      "num_citations": 19,
      "citedby_url": "https://scholar.google.com/scholar?oi=bibs&hl=en&cites=16368565002355289382",
      "cites_id": [
        "16368565002355289382"
      ]
    },
    {
      "container_type": "Publication",
      "source": "AUTHOR_PUBLICATION_ENTRY",
      "bib": {
        "title": "Energi dan Elektrifikasi Pertanian",
        "pub_year": "1998",
        "citation": "Bogor: Proyek Peningkatan Perguruan Tinggi. Institut Pertanian Bogor, 1998"
      },
      "filled": false,
      "author_pub_id": "rMcTlDwAAAAJ:aqlVkmm33-oC",
      "num_citations": 17,
      "citedby_url": "https://scholar.google.com/scholar?oi=bibs&hl=en&cites=17874002948038981887",
      "cites_id": [
        "17874002948038981887"
      ]
    },
    {
      "container_type": "Publication",
      "source": "AUTHOR_PUBLICATION_ENTRY",
      "bib": {
        "title": "Potensi Limbah Produksi Bio-Fuel Sebagai bahan bakar Alternatif",
        "pub_year": "2007",
        "citation": "IPB (Bogor Agricultural University), 2007"
      },
      "filled": false,
      "author_pub_id": "rMcTlDwAAAAJ:Wp0gIr-vW9MC",
      "num_citations": 13,
      "citedby_url": "https://scholar.google.com/scholar?oi=bibs&hl=en&cites=10854308376747915694",
      "cites_id": [
        "10854308376747915694"
      ]
    },
    {
      "container_type": "Publication",
      "source": "AUTHOR_PUBLICATION_ENTRY",
      "bib": {
        "title": "Study of temperature characterization of agricultural waste in the development of stove for combine heat power",
        "pub_year": "2017",
        "citation": "AIP conference proceedings 1826 (1), 2017"
      },
      "filled": false,
      "author_pub_id": "rMcTlDwAAAAJ:HDshCWvjkbEC",
      "num_citations": 6,
      "citedby_url": "https://scholar.google.com/scholar?oi=bibs&hl=en&cites=17760276604184620357",
      "cites_id": [
        "17760276604184620357"
      ]
    },
    {
      "container_type": "Publication",
      "source": "AUTHOR_PUBLICATION_ENTRY",
      "bib": {
        "title": "Simulasi Pengeringan Jagung Pipilan Menggunakan Alat Pengering Surya Tipe Efek Rumah Kaca (ERK)-Hybrid Dengan Pengering Silinder Berputar",
        "pub_year": "2008",
        "citation": "Jurnal Enjiniring Pertanian, 2008"
      },
      "filled": false,
      "author_pub_id": "rMcTlDwAAAAJ:QIV2ME_5wuYC",
      "num_citations": 4,
      "citedby_url": "https://scholar.google.com/scholar?oi=bibs&hl=en&cites=586364919132884371",
      "cites_id": [
        "586364919132884371"
      ]
    },
    {
      "container_type": "Publication",
      "source": "AUTHOR_PUBLICATION_ENTRY",
      "bib": {
        "title": "Pengembangan Alat Pengering Efek Rumah Kaca (Erk) Hybrid Tipe Rak Berputar Untuk Penyeragaman Alman Udara",
        "pub_year": "2008",
        "citation": ""
      },
      "filled": false,
      "author_pub_id": "rMcTlDwAAAAJ:9ZlFYXVOiuMC",
      "num_citations": 4,
      "citedby_url": "https://scholar.google.com/scholar?oi=bibs&hl=en&cites=17310025879516861611",
      "cites_id": [
        "17310025879516861611"
      ]
    },
    {
      "container_type": "Publication",
      "source": "AUTHOR_PUBLICATION_ENTRY",
      "bib": {
        "title": "THE POTENTIAL UTILIZATION OF COFFEE WASTE OF PT JAVABICA INTO BIO-BRIQUETTE AS ENVIRONMENTALLY-FRIENDLY FUEL",
        "pub_year": "2020",
        "citation": "Majalah Ilmiah Pengkajian Industri; Journal of Industrial Research and \u2026, 2020"
      },
      "filled": false,
      "author_pub_id": "rMcTlDwAAAAJ:TQgYirikUcIC",
      "num_citations": 3,
      "citedby_url": "https://scholar.google.com/scholar?oi=bibs&hl=en&cites=2690990641639318094",
      "cites_id": [
        "2690990641639318094"
      ]
    },
    {
      "container_type": "Publication",
      "source": "AUTHOR_PUBLICATION_ENTRY",
      "bib": {
        "title": "Potensi Pemanfaatan Limbah Pertanian, Perkebunan dan Agroindustri Sebagai Sumber Energi Alternatif Melalui Teknologi Brikuetting",
        "pub_year": "2003",
        "citation": "Fateta IPB: Bogor, 2003"
      },
      "filled": false,
      "author_pub_id": "rMcTlDwAAAAJ:mVmsd5A6BfQC",
      "num_citations": 3,
      "citedby_url": "https://scholar.google.com/scholar?oi=bibs&hl=en&cites=4721201906564451604",
      "cites_id": [
        "4721201906564451604"
      ]
    },
    {
      "container_type": "Publication",
      "source": "AUTHOR_PUBLICATION_ENTRY",
      "bib": {
        "title": "Implementasi Mesin Pengering Berenergi Terbarukan Hybrid (Surya Dan Biomassa) Untuk Menghasilkan Produk Jagung Pwil Yang Aman Dan Bermutu Tinggi (Implementation of Hybrid Dryer \u2026",
        "pub_year": "2009",
        "citation": "IPB (Bogor Agricultural University), 2009"
      },
      "filled": false,
      "author_pub_id": "rMcTlDwAAAAJ:hFOr9nPyWt4C",
      "num_citations": 2,
      "citedby_url": "https://scholar.google.com/scholar?oi=bibs&hl=en&cites=17070808819524198600",
      "cites_id": [
        "17070808819524198600"
      ]
    },
    {
      "container_type": "Publication",
      "source": "AUTHOR_PUBLICATION_ENTRY",
      "bib": {
        "title": "Thermal Characteristics of Coconut Shells as Boiler Fuel.",
        "pub_year": "2023",
        "citation": "International Journal of Renewable Energy Development 12 (2), 2023"
      },
      "filled": false,
      "author_pub_id": "rMcTlDwAAAAJ:R3hNpaxXUhUC",
      "num_citations": 1,
      "citedby_url": "https://scholar.google.com/scholar?oi=bibs&hl=en&cites=6772803122890460736",
      "cites_id": [
        "6772803122890460736"
      ]
    },
    {
      "container_type": "Publication",
      "source": "AUTHOR_PUBLICATION_ENTRY",
      "bib": {
        "title": "Energy Analysis On Coal Steam Power Plant Pt. Energi Alamraya Semesta",
        "pub_year": "2012",
        "citation": "IPB (Bogor Agricultural University), 2012"
      },
      "filled": false,
      "author_pub_id": "rMcTlDwAAAAJ:qUcmZB5y_30C",
      "num_citations": 1,
      "citedby_url": "https://scholar.google.com/scholar?oi=bibs&hl=en&cites=8978492895193283995",
      "cites_id": [
        "8978492895193283995"
      ]
    },
    {
      "container_type": "Publication",
      "source": "AUTHOR_PUBLICATION_ENTRY",
      "bib": {
        "title": "Sistem Pendingin dengan Fluida Kerja Air Murni",
        "pub_year": "2013",
        "citation": "IPB (Bogor Agricultural University), 2013"
      },
      "filled": false,
      "author_pub_id": "rMcTlDwAAAAJ:7PzlFSSx8tAC",
      "num_citations": 0
    },
    {
      "container_type": "Publication",
      "source": "AUTHOR_PUBLICATION_ENTRY",
      "bib": {
        "title": "DISAIN DAN UJI UNJUK KERJA MESIN PENGERING BERDASARKAN KONSEP EFEK RUMAH KACA (ERK) HIBRIDA",
        "pub_year": "2012",
        "citation": "TEKNOTAN 6 (1), 2012"
      },
      "filled": false,
      "author_pub_id": "rMcTlDwAAAAJ:L8Ckcad2t8MC",
      "num_citations": 0
    },
    {
      "container_type": "Publication",
      "source": "AUTHOR_PUBLICATION_ENTRY",
      "bib": {
        "title": "Modifikasi Disain Brander Minyak Tanah dan Disain Tungku serta Penerapannya untuk Pemasakan Gula Merah",
        "citation": "IPB (Bogor Agricultural University), 0"
      },
      "filled": false,
      "author_pub_id": "rMcTlDwAAAAJ:mB3voiENLucC",
      "num_citations": 0
    },
    {
      "container_type": "Publication",
      "source": "AUTHOR_PUBLICATION_ENTRY",
      "bib": {
        "title": "(Development of Rotary Rack Type Greenhouse Effect (GHE) Hybrid Solar Dryer to Achieve the Airflow Uniformity)",
        "citation": "IPB (Bogor Agricultural University), 0"
      },
      "filled": false,
      "author_pub_id": "rMcTlDwAAAAJ:-f6ydRqryjwC",
      "num_citations": 0
    },
    {
      "container_type": "Publication",
      "source": "AUTHOR_PUBLICATION_ENTRY",
      "bib": {
        "title": "Desain dan Uji Kinerja Tungku Pembakaran Tempurung Kelapa untuk Combined Heat and Power.",
        "citation": "IPB (Bogor Agricultural University), 0"
      },
      "filled": false,
      "author_pub_id": "rMcTlDwAAAAJ:hC7cP41nSMkC",
      "num_citations": 0
    },
    {
      "container_type": "Publication",
      "source": "AUTHOR_PUBLICATION_ENTRY",
      "bib": {
        "title": "AGENDA RISET ENERGI INSTITUT PERTA NIA N BO GOR",
        "citation": ""
      },
      "filled": false,
      "author_pub_id": "rMcTlDwAAAAJ:IWHjjKOFINEC",
      "num_citations": 0
    }
  ],
  "public_access": {
    "available": 0,
    "not_available": 0
  }
}