{
  "container_type": "Author",
  "filled": [
    "basics",
    "indices",
    "counts",
    "coauthors",
    "publications",
    "public_access"
  ],
  "scholar_id": "U4lQjr8AAAAJ",
  "source": "AUTHOR_PROFILE_PAGE",
  "name": "Gunawan Djajakirana",
  "url_picture": "https://scholar.googleusercontent.com/citations?view_op=view_photo&user=U4lQjr8AAAAJ&citpid=1",
  "affiliation": "Departemen Ilmu Tanah dan Sumberdaya Lahan, Fakultas Pertanian Institut Pertanian Bogor",
  "organization": 13375182596662322286,
  "interests": [
    "Biologi Tanah dan Lingkungan",
    "Biomassa dan Bahan Organik Tanah",
    "Kerusakan Lahan dan Remediasinya",
    "Pengomposan dan Enzim Tanah",
    "Lahan Basah dan Gambut"
  ],
  "email_domain": "@apps.ipb.ac.id",
  "citedby": 929,
  "citedby5y": 426,
  "hindex": 12,
  "hindex5y": 10,
  "i10index": 15,
  "i10index5y": 10,
  "cites_per_year": {
    "1999": 11,
    "2000": 16,
    "2001": 15,
    "2002": 11,
    "2003": 14,
    "2004": 15,
    "2005": 18,
    "2006": 25,
    "2007": 25,
    "2008": 18,
    "2009": 19,
    "2010": 32,
    "2011": 24,
    "2012": 27,
    "2013": 31,
    "2014": 37,
    "2015": 33,
    "2016": 31,
    "2017": 37,
    "2018": 49,
    "2019": 50,
    "2020": 55,
    "2021": 73,
    "2022": 101,
    "2023": 101,
    "2024": 46
  },
  "coauthors": [],
  "publications": [
    {
      "container_type": "Publication",
      "source": "AUTHOR_PUBLICATION_ENTRY",
      "bib": {
        "title": "Ergosterol and microbial biomass relationship in soil",
        "pub_year": "1996",
        "citation": "Biology and fertility of soils 22, 299-304, 1996"
      },
      "filled": false,
      "author_pub_id": "U4lQjr8AAAAJ:UeHWp8X0CEIC",
      "num_citations": 390,
      "citedby_url": "https://scholar.google.com/scholar?oi=bibs&hl=en&cites=1870741567494617784",
      "cites_id": [
        "1870741567494617784"
      ]
    },
    {
      "container_type": "Publication",
      "source": "AUTHOR_PUBLICATION_ENTRY",
      "bib": {
        "title": "Effects of an experimental drought on the functioning of a cacao agroforestry system, Sulawesi, Indonesia",
        "pub_year": "2010",
        "citation": "Global Change Biology 16 (5), 1515-1530, 2010"
      },
      "filled": false,
      "author_pub_id": "U4lQjr8AAAAJ:dhFuZR0502QC",
      "num_citations": 162,
      "citedby_url": "https://scholar.google.com/scholar?oi=bibs&hl=en&cites=14676955510855792591",
      "cites_id": [
        "14676955510855792591"
      ]
    },
    {
      "container_type": "Publication",
      "source": "AUTHOR_PUBLICATION_ENTRY",
      "bib": {
        "title": "ISOLASI DAN IDENTIFIKASI MIKROBA TANAH PENDEGRADASI SELULOSA DAN PEKTIN DARI RHIZOSFER Aquilaria malaccensis Isolation and Identification of Cellulose and Pectin-Degrading Soil \u2026",
        "pub_year": "2017",
        "citation": ""
      },
      "filled": false,
      "author_pub_id": "U4lQjr8AAAAJ:hC7cP41nSMkC",
      "num_citations": 43,
      "citedby_url": "https://scholar.google.com/scholar?oi=bibs&hl=en&cites=882408338049368244",
      "cites_id": [
        "882408338049368244"
      ]
    },
    {
      "container_type": "Publication",
      "source": "AUTHOR_PUBLICATION_ENTRY",
      "bib": {
        "title": "Application of biochar and organic fertilizer on acid soil as growing medium for Cacao (Theobroma cacao L.) seedlings",
        "pub_year": "2017",
        "citation": "International Journal of Sciences Basic and Applied Research 36 (5), 261-273, 2017"
      },
      "filled": false,
      "author_pub_id": "U4lQjr8AAAAJ:Wp0gIr-vW9MC",
      "num_citations": 34,
      "citedby_url": "https://scholar.google.com/scholar?oi=bibs&hl=en&cites=1669132770858538712",
      "cites_id": [
        "1669132770858538712"
      ]
    },
    {
      "container_type": "Publication",
      "source": "AUTHOR_PUBLICATION_ENTRY",
      "bib": {
        "title": "Prospek cacing tanah untuk pengembangan teknologi resapan biologi di lahan kering",
        "pub_year": "2008",
        "citation": "Jurnal Litbang Pertanian 27 (4), 146-150, 2008"
      },
      "filled": false,
      "author_pub_id": "U4lQjr8AAAAJ:j3f4tGmQtD8C",
      "num_citations": 27,
      "citedby_url": "https://scholar.google.com/scholar?oi=bibs&hl=en&cites=10937373020003658773",
      "cites_id": [
        "10937373020003658773"
      ]
    },
    {
      "container_type": "Publication",
      "source": "AUTHOR_PUBLICATION_ENTRY",
      "bib": {
        "title": "HUBUNGAN PARAMETER ARUS LAUT DAN LIFEFORM KARANG PADA BEBERAPA PULAU-PULAU KECIL DI KOTA PADANG:(The Relationship of Ocean Current Parameters and Coral Lifeform in Small \u2026",
        "pub_year": "2023",
        "citation": "Majalah Ilmiah Globe 25 (1), 1-12, 2023"
      },
      "filled": false,
      "author_pub_id": "U4lQjr8AAAAJ:TQgYirikUcIC",
      "num_citations": 25,
      "citedby_url": "https://scholar.google.com/scholar?oi=bibs&hl=en&cites=17746601089339986720",
      "cites_id": [
        "17746601089339986720"
      ]
    },
    {
      "container_type": "Publication",
      "source": "AUTHOR_PUBLICATION_ENTRY",
      "bib": {
        "title": "Nutrient release performance of starch coated NPK fertilizers and their effects on Corn growth",
        "pub_year": "2018",
        "citation": "SAINS TANAH-Journal of Soil Science and Agroclimatology 15 (2), 104-114, 2018"
      },
      "filled": false,
      "author_pub_id": "U4lQjr8AAAAJ:4JMBOYKVnBMC",
      "num_citations": 23,
      "citedby_url": "https://scholar.google.com/scholar?oi=bibs&hl=en&cites=16197831932781971869",
      "cites_id": [
        "16197831932781971869"
      ]
    },
    {
      "container_type": "Publication",
      "source": "AUTHOR_PUBLICATION_ENTRY",
      "bib": {
        "title": "Pemanfaatan cacing tanah untuk meningkatkan produktivitas Ultisols lahan kering",
        "pub_year": "2002",
        "citation": "J. Tanah dan Iklim 20, 35-46, 2002"
      },
      "filled": false,
      "author_pub_id": "U4lQjr8AAAAJ:qjMakFHDy7sC",
      "num_citations": 18,
      "citedby_url": "https://scholar.google.com/scholar?oi=bibs&hl=en&cites=1374062900854836190",
      "cites_id": [
        "1374062900854836190"
      ]
    },
    {
      "container_type": "Publication",
      "source": "AUTHOR_PUBLICATION_ENTRY",
      "bib": {
        "title": "Changes in soil organic matter, microbial biomass C and ergosterol under a fairy ring of Marasmius oreades",
        "pub_year": "1996",
        "citation": "Pedobiologia 40 (6), 498-504, 1996"
      },
      "filled": false,
      "author_pub_id": "U4lQjr8AAAAJ:4DMP91E08xMC",
      "num_citations": 18,
      "citedby_url": "https://scholar.google.com/scholar?oi=bibs&hl=en&cites=13043568888532725621",
      "cites_id": [
        "13043568888532725621"
      ]
    },
    {
      "container_type": "Publication",
      "source": "AUTHOR_PUBLICATION_ENTRY",
      "bib": {
        "title": "Pengaruh Pupuk Organik dan Arang Hayati terhadap Kualitas Media Pembibitan dan Pertumbuhan Bibit Cacao",
        "pub_year": "2017",
        "citation": "Jurnal Tanaman Industri Dan Penyegar 4 (2), 107-120, 2017"
      },
      "filled": false,
      "author_pub_id": "U4lQjr8AAAAJ:BqipwSGYUEgC",
      "num_citations": 16,
      "citedby_url": "https://scholar.google.com/scholar?oi=bibs&hl=en&cites=1089189188763269648",
      "cites_id": [
        "1089189188763269648"
      ]
    },
    {
      "container_type": "Publication",
      "source": "AUTHOR_PUBLICATION_ENTRY",
      "bib": {
        "title": "Kerusakan tanah sebagai dampak pembangunan pertanian",
        "pub_year": "2001",
        "citation": "Makalah disampaikan pada seminar petani \u201cTanah sehat titik tumbuh pertanian \u2026, 2001"
      },
      "filled": false,
      "author_pub_id": "U4lQjr8AAAAJ:kNdYIx-mwKoC",
      "num_citations": 16,
      "citedby_url": "https://scholar.google.com/scholar?oi=bibs&hl=en&cites=9050708991256719972",
      "cites_id": [
        "9050708991256719972"
      ]
    },
    {
      "container_type": "Publication",
      "source": "AUTHOR_PUBLICATION_ENTRY",
      "bib": {
        "title": "Proses Pembuatan, Pemanfaatan dan Pemasaran Vermikompos untuk Pertanian di Indonesia",
        "pub_year": "2002",
        "citation": "Makalah disampaikan pada Seminar \u201cPemanfaatan Teknologi Aplikatif Pertanian \u2026, 2002"
      },
      "filled": false,
      "author_pub_id": "U4lQjr8AAAAJ:maZDTaKrznsC",
      "num_citations": 12,
      "citedby_url": "https://scholar.google.com/scholar?oi=bibs&hl=en&cites=9881776053731720835",
      "cites_id": [
        "9881776053731720835"
      ]
    },
    {
      "container_type": "Publication",
      "source": "AUTHOR_PUBLICATION_ENTRY",
      "bib": {
        "title": "Concentration of some trace elements in two wild edible ferns, Diplazium esculentum and Stenochlaena palutris, inhabiting tropical peatlands under different environments in \u2026",
        "pub_year": "2017",
        "citation": "Eurasian Journal of Forest Research 20, 11-20, 2017"
      },
      "filled": false,
      "author_pub_id": "U4lQjr8AAAAJ:roLk4NBRz8UC",
      "num_citations": 11,
      "citedby_url": "https://scholar.google.com/scholar?oi=bibs&hl=en&cites=7311828788202114299",
      "cites_id": [
        "7311828788202114299"
      ]
    },
    {
      "container_type": "Publication",
      "source": "AUTHOR_PUBLICATION_ENTRY",
      "bib": {
        "title": "The diversity and abundance of springtail (Collembola) on forests and smallholder in Jambi",
        "pub_year": "2016",
        "citation": "Journal of Tropical Soils 20 (3), 173-180, 2016"
      },
      "filled": false,
      "author_pub_id": "U4lQjr8AAAAJ:isC4tDSrTZIC",
      "num_citations": 10,
      "citedby_url": "https://scholar.google.com/scholar?oi=bibs&hl=en&cites=10010297626542669172",
      "cites_id": [
        "10010297626542669172"
      ]
    },
    {
      "container_type": "Publication",
      "source": "AUTHOR_PUBLICATION_ENTRY",
      "bib": {
        "title": "Metode-Metode Penetapan Biomassa Mikroorganisme Tanah secara Langsung dan Tidak Langsung: Kelemaahn dan Keunggulannya (Direct and Indirect Methods of Soil Microbial-Biomass \u2026",
        "pub_year": "2003",
        "citation": "Jurnal Ilmu Tanah Dan Lingkungan 5 (1), 29-38, 2003"
      },
      "filled": false,
      "author_pub_id": "U4lQjr8AAAAJ:u-x6o8ySG0sC",
      "num_citations": 10,
      "citedby_url": "https://scholar.google.com/scholar?oi=bibs&hl=en&cites=437259886727142002",
      "cites_id": [
        "437259886727142002"
      ]
    },
    {
      "container_type": "Publication",
      "source": "AUTHOR_PUBLICATION_ENTRY",
      "bib": {
        "title": "Perubahan fraksi bahan organik tanah akibat perbedaan cara pemberian dan sumber bahan organik pada ultisols jasinga",
        "pub_year": "2007",
        "citation": "Jurnal Tanah dan Iklim 26, 29-40, 2007"
      },
      "filled": false,
      "author_pub_id": "U4lQjr8AAAAJ:4OULZ7Gr8RgC",
      "num_citations": 8,
      "citedby_url": "https://scholar.google.com/scholar?oi=bibs&hl=en&cites=12163683494816998068",
      "cites_id": [
        "12163683494816998068"
      ]
    },
    {
      "container_type": "Publication",
      "source": "AUTHOR_PUBLICATION_ENTRY",
      "bib": {
        "title": "Characteristics of Biochars from Plant Biomass Wastes at Low-Temperature Pyrolysis",
        "pub_year": "2018",
        "citation": "SAINS TANAH-Journal of Soil Science and Agroclimatology 15 (1), 15-28, 2018"
      },
      "filled": false,
      "author_pub_id": "U4lQjr8AAAAJ:RHpTSmoSYBkC",
      "num_citations": 7,
      "citedby_url": "https://scholar.google.com/scholar?oi=bibs&hl=en&cites=1241463374981463954",
      "cites_id": [
        "1241463374981463954"
      ]
    },
    {
      "container_type": "Publication",
      "source": "AUTHOR_PUBLICATION_ENTRY",
      "bib": {
        "title": "Slow-release fertilizer formulation using acrylic and chitosan coating",
        "pub_year": "2016",
        "citation": "Journal of Tropical Soils 20 (1), 37-45, 2016"
      },
      "filled": false,
      "author_pub_id": "U4lQjr8AAAAJ:aqlVkmm33-oC",
      "num_citations": 7,
      "citedby_url": "https://scholar.google.com/scholar?oi=bibs&hl=en&cites=13024563202819104486",
      "cites_id": [
        "13024563202819104486"
      ]
    },
    {
      "container_type": "Publication",
      "source": "AUTHOR_PUBLICATION_ENTRY",
      "bib": {
        "title": "The contribution of organic acid on heterotrophic CO2 flux from tropical peat: a trenching study",
        "pub_year": "2021",
        "citation": "Journal of Degraded and Mining Lands Management 9 (1), 3035, 2021"
      },
      "filled": false,
      "author_pub_id": "U4lQjr8AAAAJ:B3FOqHPlNUQC",
      "num_citations": 6,
      "citedby_url": "https://scholar.google.com/scholar?oi=bibs&hl=en&cites=11231275638605535180",
      "cites_id": [
        "11231275638605535180"
      ]
    },
    {
      "container_type": "Publication",
      "source": "AUTHOR_PUBLICATION_ENTRY",
      "bib": {
        "title": "Potensi Limbah Tahu untuk Menghasilkan Listrik pada Tiga Model Sistem Microbial Fuel Cell (MFC)",
        "pub_year": "2020",
        "citation": "Jurnal Ilmu Tanah dan Lingkungan 22 (1), 29-34, 2020"
      },
      "filled": false,
      "author_pub_id": "U4lQjr8AAAAJ:NhqRSupF_l8C",
      "num_citations": 6,
      "citedby_url": "https://scholar.google.com/scholar?oi=bibs&hl=en&cites=2628528016440187212",
      "cites_id": [
        "2628528016440187212"
      ]
    },
    {
      "container_type": "Publication",
      "source": "AUTHOR_PUBLICATION_ENTRY",
      "bib": {
        "title": "Karakterisasi dan resiliensi tanah terdegradasi di lahan kering Kalimantan Tengah",
        "pub_year": "2007",
        "citation": "IPB (Bogor Agricultural University), 2007"
      },
      "filled": false,
      "author_pub_id": "U4lQjr8AAAAJ:D_sINldO8mEC",
      "num_citations": 6,
      "citedby_url": "https://scholar.google.com/scholar?oi=bibs&hl=en&cites=11869996703645451131",
      "cites_id": [
        "11869996703645451131"
      ]
    },
    {
      "container_type": "Publication",
      "source": "AUTHOR_PUBLICATION_ENTRY",
      "bib": {
        "title": "Keanekaragaman dan fluktuasi kelimpahan Collembola di sekitar tanaman kelapa sawit di perkebunan Cikasungka, Kabupaten Bogor",
        "pub_year": "2016",
        "citation": "Jurnal Entomologi Indonesia 13 (2), 99-99, 2016"
      },
      "filled": false,
      "author_pub_id": "U4lQjr8AAAAJ:LkGwnXOMwfcC",
      "num_citations": 5,
      "citedby_url": "https://scholar.google.com/scholar?oi=bibs&hl=en&cites=17479489520031354091,17822482224629609696",
      "cites_id": [
        "17479489520031354091",
        "17822482224629609696"
      ]
    },
    {
      "container_type": "Publication",
      "source": "AUTHOR_PUBLICATION_ENTRY",
      "bib": {
        "title": "Metode Alternatif Memperkirakan Konsentrasi Karbon Organik Terlarut dalam Air Saluran Drainase dan Tanah Gambut",
        "pub_year": "2015",
        "citation": "Jurnal Tanah dan Iklim 39 (1), 1-8, 2015"
      },
      "filled": false,
      "author_pub_id": "U4lQjr8AAAAJ:8k81kl-MbHgC",
      "num_citations": 5,
      "citedby_url": "https://scholar.google.com/scholar?oi=bibs&hl=en&cites=8382234668356643595",
      "cites_id": [
        "8382234668356643595"
      ]
    },
    {
      "container_type": "Publication",
      "source": "AUTHOR_PUBLICATION_ENTRY",
      "bib": {
        "title": "Some considerations of tropical peat for energy",
        "pub_year": "2007",
        "citation": "Carbon\u2013Climate\u2013Human Interaction on Tropical Peatland: Proceedings of the \u2026, 2007"
      },
      "filled": false,
      "author_pub_id": "U4lQjr8AAAAJ:u5HHmVD_uO8C",
      "num_citations": 5,
      "citedby_url": "https://scholar.google.com/scholar?oi=bibs&hl=en&cites=264673757713674238",
      "cites_id": [
        "264673757713674238"
      ]
    },
    {
      "container_type": "Publication",
      "source": "AUTHOR_PUBLICATION_ENTRY",
      "bib": {
        "title": "Kajian perbaikan teknologi budidaya cacing tanah Eisenia foetida Savigny untuk meningkatkan produksi biomassa dan kualitas eksmecat dengan memanfaatkan limbah organik sebagai media",
        "pub_year": "2001",
        "citation": "Media Peternakan 24 (1), 28-38, 2001"
      },
      "filled": false,
      "author_pub_id": "U4lQjr8AAAAJ:e5wmG9Sq2KIC",
      "num_citations": 5,
      "citedby_url": "https://scholar.google.com/scholar?oi=bibs&hl=en&cites=11294774227297261556",
      "cites_id": [
        "11294774227297261556"
      ]
    },
    {
      "container_type": "Publication",
      "source": "AUTHOR_PUBLICATION_ENTRY",
      "bib": {
        "title": "Die Messung von Ergosterol in B\u00f6den",
        "pub_year": "1993",
        "citation": "Mitteilungen der DBG 71, 317-318, 1993"
      },
      "filled": false,
      "author_pub_id": "U4lQjr8AAAAJ:EUQCXRtRnyEC",
      "num_citations": 5,
      "citedby_url": "https://scholar.google.com/scholar?oi=bibs&hl=en&cites=17860860550394130965",
      "cites_id": [
        "17860860550394130965"
      ]
    },
    {
      "container_type": "Publication",
      "source": "AUTHOR_PUBLICATION_ENTRY",
      "bib": {
        "title": "Harvesting bioelectricity from microbial fuel cells (MFCs) powered by electroactive microbes",
        "pub_year": "2023",
        "citation": "Jurnal Teknik Pertanian Lampung (Journal of Agricultural Engineering) 12 (3 \u2026, 2023"
      },
      "filled": false,
      "author_pub_id": "U4lQjr8AAAAJ:kRWSkSYxWN8C",
      "num_citations": 4,
      "citedby_url": "https://scholar.google.com/scholar?oi=bibs&hl=en&cites=12168521265088409213",
      "cites_id": [
        "12168521265088409213"
      ]
    },
    {
      "container_type": "Publication",
      "source": "AUTHOR_PUBLICATION_ENTRY",
      "bib": {
        "title": "Pengaruh penambahan kompos kotoran sapi dan FABA terhadap karakteristik kimia pada tanah berpasir dan pertumbuhan tanaman tomat",
        "pub_year": "2022",
        "citation": "Jurnal Ilmu Tanah dan Lingkungan 24 (1), 1-5, 2022"
      },
      "filled": false,
      "author_pub_id": "U4lQjr8AAAAJ:5Ul4iDaHHb8C",
      "num_citations": 4,
      "citedby_url": "https://scholar.google.com/scholar?oi=bibs&hl=en&cites=15795410627423752119",
      "cites_id": [
        "15795410627423752119"
      ]
    },
    {
      "container_type": "Publication",
      "source": "AUTHOR_PUBLICATION_ENTRY",
      "bib": {
        "title": "Fluks Metana dan Karakteristik Tanah pada Beberapa Macam Sistem Budidaya",
        "pub_year": "2006",
        "citation": "Indonesian Journal of Agronomy 34 (3), 7957, 2006"
      },
      "filled": false,
      "author_pub_id": "U4lQjr8AAAAJ:bEWYMUwI8FkC",
      "num_citations": 4,
      "citedby_url": "https://scholar.google.com/scholar?oi=bibs&hl=en&cites=3172627062888387500",
      "cites_id": [
        "3172627062888387500"
      ]
    },
    {
      "container_type": "Publication",
      "source": "AUTHOR_PUBLICATION_ENTRY",
      "bib": {
        "title": "Pembuatan dan Aplikasi Pupuk Organik Cair (POC) Sebagai Substitusi Nutrisi AB Mix Terhadap Tanaman Kangkung (Ipomoea reptans) Pada Hidroponik Wick System",
        "pub_year": "2023",
        "citation": "Jurnal Tanah dan Sumberdaya Lahan 10 (2), 401-407, 2023"
      },
      "filled": false,
      "author_pub_id": "U4lQjr8AAAAJ:q3oQSFYPqjQC",
      "num_citations": 3,
      "citedby_url": "https://scholar.google.com/scholar?oi=bibs&hl=en&cites=11761684684470610918",
      "cites_id": [
        "11761684684470610918"
      ]
    },
    {
      "container_type": "Publication",
      "source": "AUTHOR_PUBLICATION_ENTRY",
      "bib": {
        "title": "Application of phosphate solubilizing microbes to promote the effectiveness of rock phosphate on cacao seedling growth in acid soil",
        "pub_year": "2022",
        "citation": "AIP Conference Proceedings 2462 (1), 2022"
      },
      "filled": false,
      "author_pub_id": "U4lQjr8AAAAJ:8AbLer7MMksC",
      "num_citations": 3,
      "citedby_url": "https://scholar.google.com/scholar?oi=bibs&hl=en&cites=6950118508802759848",
      "cites_id": [
        "6950118508802759848"
      ]
    },
    {
      "container_type": "Publication",
      "source": "AUTHOR_PUBLICATION_ENTRY",
      "bib": {
        "title": "Controls on the net dissolved organic carbon production in tropical peat",
        "pub_year": "2020",
        "citation": "SAINS TANAH-Journal of Soil Science and Agroclimatology 17 (2), 161-169, 2020"
      },
      "filled": false,
      "author_pub_id": "U4lQjr8AAAAJ:xtRiw3GOFMkC",
      "num_citations": 3,
      "citedby_url": "https://scholar.google.com/scholar?oi=bibs&hl=en&cites=2498938069111663321",
      "cites_id": [
        "2498938069111663321"
      ]
    },
    {
      "container_type": "Publication",
      "source": "AUTHOR_PUBLICATION_ENTRY",
      "bib": {
        "title": "Bioelectricity production of microbial fuel cells (MFCs) and the simultaneous monitoring using developed multi-channels Arduino UNO-based data logging system",
        "pub_year": "2024",
        "citation": "Journal of Applied Electrochemistry 54 (3), 503-518, 2024"
      },
      "filled": false,
      "author_pub_id": "U4lQjr8AAAAJ:eq2jaN3J8jMC",
      "num_citations": 2,
      "citedby_url": "https://scholar.google.com/scholar?oi=bibs&hl=en&cites=16836407377199334004",
      "cites_id": [
        "16836407377199334004"
      ]
    },
    {
      "container_type": "Publication",
      "source": "AUTHOR_PUBLICATION_ENTRY",
      "bib": {
        "title": "PENGARUH MEDIA TANAM TERHADAP PERTUMBUHAN BIBIT TANAMAN CABAI (Capsicum annuum L) DAN INTENSITAS SERANGAN LAYU FUSARIUM (Fusarium oxysporum Schlecth) PADA PEMBIBITANNYA",
        "pub_year": "2022",
        "citation": "Jurnal Ilmu Tanah Dan Lingkungan 24 (2), 62-66, 2022"
      },
      "filled": false,
      "author_pub_id": "U4lQjr8AAAAJ:VOx2b1Wkg3QC",
      "num_citations": 2,
      "citedby_url": "https://scholar.google.com/scholar?oi=bibs&hl=en&cites=14042516772832746892",
      "cites_id": [
        "14042516772832746892"
      ]
    },
    {
      "container_type": "Publication",
      "source": "AUTHOR_PUBLICATION_ENTRY",
      "bib": {
        "title": "Fungi Dekomposer Penghasil Enzim Ekstraseluler Lakase, Mangan Peroksidase, dan Lignin Peroksidase dari Kawasan Kebun Raya Bogor: Isolasi, Seleksi, Identifikasi dan Kajian \u2026",
        "pub_year": "2022",
        "citation": "Jurnal Biologi Indonesia 18 (1), 111-119, 2022"
      },
      "filled": false,
      "author_pub_id": "U4lQjr8AAAAJ:LPZeul_q3PIC",
      "num_citations": 2,
      "citedby_url": "https://scholar.google.com/scholar?oi=bibs&hl=en&cites=2595079641143628570",
      "cites_id": [
        "2595079641143628570"
      ]
    },
    {
      "container_type": "Publication",
      "source": "AUTHOR_PUBLICATION_ENTRY",
      "bib": {
        "title": "Producing renewable electric energy through a microbial fuel cell in the rice field",
        "pub_year": "2020",
        "citation": "Biodiversitas Journal of Biological Diversity 21 (9), 2020"
      },
      "filled": false,
      "author_pub_id": "U4lQjr8AAAAJ:abG-DnoFyZgC",
      "num_citations": 2,
      "citedby_url": "https://scholar.google.com/scholar?oi=bibs&hl=en&cites=17433820192402458309",
      "cites_id": [
        "17433820192402458309"
      ]
    },
    {
      "container_type": "Publication",
      "source": "AUTHOR_PUBLICATION_ENTRY",
      "bib": {
        "title": "Understanding nutrient cycles as a key to sustainable forest plantation on tropical peatland in Indonesia",
        "pub_year": "2019",
        "citation": "IOP Conference Series: Earth and Environmental Science 393 (1), 012029, 2019"
      },
      "filled": false,
      "author_pub_id": "U4lQjr8AAAAJ:cFHS6HbyZ2cC",
      "num_citations": 2,
      "citedby_url": "https://scholar.google.com/scholar?oi=bibs&hl=en&cites=4863024505398739428",
      "cites_id": [
        "4863024505398739428"
      ]
    },
    {
      "container_type": "Publication",
      "source": "AUTHOR_PUBLICATION_ENTRY",
      "bib": {
        "title": "Isolasi dan seleksi galur Bradyrhizobium japonicum asal tanah gambut",
        "pub_year": "2002",
        "citation": "IPB (Bogor Agricultural University), 2002"
      },
      "filled": false,
      "author_pub_id": "U4lQjr8AAAAJ:hFOr9nPyWt4C",
      "num_citations": 2,
      "citedby_url": "https://scholar.google.com/scholar?oi=bibs&hl=en&cites=17267010316274061258",
      "cites_id": [
        "17267010316274061258"
      ]
    },
    {
      "container_type": "Publication",
      "source": "AUTHOR_PUBLICATION_ENTRY",
      "bib": {
        "title": "Assessing N2O Emissions from Tropical Crop Cultivation in Mineral and Peatland Soils: A Review",
        "citation": "Caraka Tani: Journal of Sustainable Agriculture 38 (2), 308-326, 0"
      },
      "filled": false,
      "author_pub_id": "U4lQjr8AAAAJ:dTyEYWd-f8wC",
      "num_citations": 2,
      "citedby_url": "https://scholar.google.com/scholar?oi=bibs&hl=en&cites=4535892940841009707",
      "cites_id": [
        "4535892940841009707"
      ]
    },
    {
      "container_type": "Publication",
      "source": "AUTHOR_PUBLICATION_ENTRY",
      "bib": {
        "title": "Bioelectrochemical assessment of a novel electrogenic Bacillus altitudinis AC11.2 for electricity generation in microbial fuel cell (MFC) system",
        "pub_year": "2024",
        "citation": "Journal of Applied Electrochemistry 54 (5), 977-997, 2024"
      },
      "filled": false,
      "author_pub_id": "U4lQjr8AAAAJ:5awf1xo2G04C",
      "num_citations": 1,
      "citedby_url": "https://scholar.google.com/scholar?oi=bibs&hl=en&cites=1463107081059371209",
      "cites_id": [
        "1463107081059371209"
      ]
    },
    {
      "container_type": "Publication",
      "source": "AUTHOR_PUBLICATION_ENTRY",
      "bib": {
        "title": "Affordable ESP32-based monitoring system for microbial fuel cells: real-time analysis and performance evaluation (ESP32-based data logger as a monitoring system for microbial \u2026",
        "pub_year": "2023",
        "citation": "International Journal of Energy and Water Resources, 1-14, 2023"
      },
      "filled": false,
      "author_pub_id": "U4lQjr8AAAAJ:SdhP9T11ey4C",
      "num_citations": 1,
      "citedby_url": "https://scholar.google.com/scholar?oi=bibs&hl=en&cites=17015054814209210758",
      "cites_id": [
        "17015054814209210758"
      ]
    },
    {
      "container_type": "Publication",
      "source": "AUTHOR_PUBLICATION_ENTRY",
      "bib": {
        "title": "Endophytic Testing of Serratia marcescens strain NPKC3_2_21 against Inpara 3 Rice Variety",
        "pub_year": "2023",
        "citation": "BIOVALENTIA: Biological Research Journal 9 (1), 48-55, 2023"
      },
      "filled": false,
      "author_pub_id": "U4lQjr8AAAAJ:1qzjygNMrQYC",
      "num_citations": 1,
      "citedby_url": "https://scholar.google.com/scholar?oi=bibs&hl=en&cites=12394650000988702539",
      "cites_id": [
        "12394650000988702539"
      ]
    },
    {
      "container_type": "Publication",
      "source": "AUTHOR_PUBLICATION_ENTRY",
      "bib": {
        "title": "Aplikasi Kombinasi Biochar dan Pupuk Hayati pada Tanaman Jagung di Lahan Kering Kabupaten Pandeglang",
        "pub_year": "2022",
        "citation": "Jurnal Ilmu Tanah dan Lingkungan 24 (2), 47-52, 2022"
      },
      "filled": false,
      "author_pub_id": "U4lQjr8AAAAJ:fQNAKQ3IYiAC",
      "num_citations": 1,
      "citedby_url": "https://scholar.google.com/scholar?oi=bibs&hl=en&cites=11270534483190838481",
      "cites_id": [
        "11270534483190838481"
      ]
    },
    {
      "container_type": "Publication",
      "source": "AUTHOR_PUBLICATION_ENTRY",
      "bib": {
        "title": "On the development of measurement procedure of particle density for peat material",
        "pub_year": "2019",
        "citation": "IOP Conference Series: Earth and Environmental Science 393 (1), 012056, 2019"
      },
      "filled": false,
      "author_pub_id": "U4lQjr8AAAAJ:a0OBvERweLwC",
      "num_citations": 1,
      "citedby_url": "https://scholar.google.com/scholar?oi=bibs&hl=en&cites=18099316480288584127",
      "cites_id": [
        "18099316480288584127"
      ]
    },
    {
      "container_type": "Publication",
      "source": "AUTHOR_PUBLICATION_ENTRY",
      "bib": {
        "title": "Spatial analysis of hotspot data for tracing the source of annual peat fires in South Sumatera, Indonesia",
        "pub_year": "2019",
        "citation": "IOP Conference Series: Earth and Environmental Science 393 (1), 012068, 2019"
      },
      "filled": false,
      "author_pub_id": "U4lQjr8AAAAJ:yD5IFk8b50cC",
      "num_citations": 1,
      "citedby_url": "https://scholar.google.com/scholar?oi=bibs&hl=en&cites=16231160478321293590",
      "cites_id": [
        "16231160478321293590"
      ]
    },
    {
      "container_type": "Publication",
      "source": "AUTHOR_PUBLICATION_ENTRY",
      "bib": {
        "title": "Effect of Organic Fertilizer and Biochar on Seedling Media Quality and Growth of Cacao Seedling",
        "pub_year": "2017",
        "citation": "Journal of Industrial and Beverage Crops 4 (2), 107-120, 2017"
      },
      "filled": false,
      "author_pub_id": "U4lQjr8AAAAJ:9ZlFYXVOiuMC",
      "num_citations": 1,
      "citedby_url": "https://scholar.google.com/scholar?oi=bibs&hl=en&cites=14379836274909728370",
      "cites_id": [
        "14379836274909728370"
      ]
    },
    {
      "container_type": "Publication",
      "source": "AUTHOR_PUBLICATION_ENTRY",
      "bib": {
        "title": "Metode Penetapan Mesofauna Tanah pada Areal Lahan Gambut di Teluk Meranti, Kabupaten Pelalawan, Provinsi Riau",
        "pub_year": "2015",
        "citation": ""
      },
      "filled": false,
      "author_pub_id": "U4lQjr8AAAAJ:K3LRdlH-MEoC",
      "num_citations": 1,
      "citedby_url": "https://scholar.google.com/scholar?oi=bibs&hl=en&cites=6663668918634490029",
      "cites_id": [
        "6663668918634490029"
      ]
    },
    {
      "container_type": "Publication",
      "source": "AUTHOR_PUBLICATION_ENTRY",
      "bib": {
        "title": "Use of earthworm to increase upland ultisols productivity",
        "pub_year": "2012",
        "citation": "Jurnal Tanah dan Iklim, 2012"
      },
      "filled": false,
      "author_pub_id": "U4lQjr8AAAAJ:QIV2ME_5wuYC",
      "num_citations": 1,
      "citedby_url": "https://scholar.google.com/scholar?oi=bibs&hl=en&cites=14475590671788678464",
      "cites_id": [
        "14475590671788678464"
      ]
    },
    {
      "container_type": "Publication",
      "source": "AUTHOR_PUBLICATION_ENTRY",
      "bib": {
        "title": "Nutrient cycle in Acacia crassicarpa plantation on deep tropical peatland at Bukitbatu, Bengkalis, Indonesia",
        "pub_year": "2011",
        "citation": "ESAFS, 2011"
      },
      "filled": false,
      "author_pub_id": "U4lQjr8AAAAJ:XiVPGOgt02cC",
      "num_citations": 1,
      "citedby_url": "https://scholar.google.com/scholar?oi=bibs&hl=en&cites=2075960170958693478",
      "cites_id": [
        "2075960170958693478"
      ]
    },
    {
      "container_type": "Publication",
      "source": "AUTHOR_PUBLICATION_ENTRY",
      "bib": {
        "title": "Study Improvement Of Indonesian Acid Sulphate Soil: Ameliorant For Masking Aluminum Toxicity In Rice Plant",
        "pub_year": "2009",
        "citation": "IPB (Bogor Agricultural University), 2009"
      },
      "filled": false,
      "author_pub_id": "U4lQjr8AAAAJ:NaGl4SEjCO4C",
      "num_citations": 1,
      "citedby_url": "https://scholar.google.com/scholar?oi=bibs&hl=en&cites=1583690422173000540,9831374886365693076",
      "cites_id": [
        "1583690422173000540",
        "9831374886365693076"
      ]
    },
    {
      "container_type": "Publication",
      "source": "AUTHOR_PUBLICATION_ENTRY",
      "bib": {
        "title": "Keselarasan penyediaan nitrogen dari pupuk hijau dan urea dengan pertumbuhan jagung pada inceptisol Darmaga",
        "pub_year": "2007",
        "citation": "Jurnal Agronomi Indonesia (Indonesian Journal of Agronomy) 35 (3), 2007"
      },
      "filled": false,
      "author_pub_id": "U4lQjr8AAAAJ:L8Ckcad2t8MC",
      "num_citations": 1,
      "citedby_url": "https://scholar.google.com/scholar?oi=bibs&hl=en&cites=15910911171791590472",
      "cites_id": [
        "15910911171791590472"
      ]
    },
    {
      "container_type": "Publication",
      "source": "AUTHOR_PUBLICATION_ENTRY",
      "bib": {
        "title": "ISOLASI DAN UJI AKTIVITAS BAKTERI ASIDOFILIK PENGOKSIDASI BESI DAN SULFUR DAR! EKOSISTEM AIR HITAM DI KALIMANTAN TENGAH",
        "pub_year": "2004",
        "citation": "Jurnal Ilmu Tanah dan Lingkungan 6 (2), 51-56, 2004"
      },
      "filled": false,
      "author_pub_id": "U4lQjr8AAAAJ:_xSYboBqXhAC",
      "num_citations": 1,
      "citedby_url": "https://scholar.google.com/scholar?oi=bibs&hl=en&cites=5556848459833959925",
      "cites_id": [
        "5556848459833959925"
      ]
    },
    {
      "container_type": "Publication",
      "source": "AUTHOR_PUBLICATION_ENTRY",
      "bib": {
        "title": "Isolation and Activity Test of Acidophilic Iron and Sulfur Oxidizing Bacteria from Black Water Ecosystem of Central Kalimantan",
        "pub_year": "2004",
        "citation": "IPB (Bogor Agricultural University), 2004"
      },
      "filled": false,
      "author_pub_id": "U4lQjr8AAAAJ:PELIpwtuRlgC",
      "num_citations": 1,
      "citedby_url": "https://scholar.google.com/scholar?oi=bibs&hl=en&cites=16455407566203804404",
      "cites_id": [
        "16455407566203804404"
      ]
    },
    {
      "container_type": "Publication",
      "source": "AUTHOR_PUBLICATION_ENTRY",
      "bib": {
        "title": "Relationship of the groundwater level with soil CO2 emission in drained peatland",
        "pub_year": "2024",
        "citation": "AIP Conference Proceedings 2957 (1), 2024"
      },
      "filled": false,
      "author_pub_id": "U4lQjr8AAAAJ:JQOojiI6XY0C",
      "num_citations": 0
    },
    {
      "container_type": "Publication",
      "source": "AUTHOR_PUBLICATION_ENTRY",
      "bib": {
        "title": "Effectiveness of potassium humate and endophytic bacteria from Serratia marcescens strain NPKC3_2_21 in increasing root weight of paddy cultivation in acidic soil",
        "pub_year": "2023",
        "citation": "Biodiversitas Journal of Biological Diversity 24 (11), 2023"
      },
      "filled": false,
      "author_pub_id": "U4lQjr8AAAAJ:WqliGbK-hY8C",
      "num_citations": 0
    },
    {
      "container_type": "Publication",
      "source": "AUTHOR_PUBLICATION_ENTRY",
      "bib": {
        "title": "Nutrient release from decomposition of A. mangium and Nephrolepis sp. litter",
        "pub_year": "2023",
        "citation": "IOP Conference Series: Earth and Environmental Science 1266 (1), 012070, 2023"
      },
      "filled": false,
      "author_pub_id": "U4lQjr8AAAAJ:LjlpjdlvIbIC",
      "num_citations": 0
    },
    {
      "container_type": "Publication",
      "source": "AUTHOR_PUBLICATION_ENTRY",
      "bib": {
        "title": "Pengaruh Pemberian Kompos Pada Pertumbuhan dan Produktivitas Tanaman Bawang Merah (Allium cepa L.)",
        "pub_year": "2023",
        "citation": "Jurnal Ilmu Pertanian Indonesia 28 (4), 534-545, 2023"
      },
      "filled": false,
      "author_pub_id": "U4lQjr8AAAAJ:9vf0nzSNQJEC",
      "num_citations": 0
    },
    {
      "container_type": "Publication",
      "source": "AUTHOR_PUBLICATION_ENTRY",
      "bib": {
        "title": "Respon Pemberian Kompos Terhadap Pertumbuhan dan Produktivitas Tanaman Bawang Merah (Allium cepa L.)",
        "pub_year": "2023",
        "citation": "Jurnal Ilmu Pertanian Indonesia, 2023"
      },
      "filled": false,
      "author_pub_id": "U4lQjr8AAAAJ:mvPsJ3kp5DgC",
      "num_citations": 0
    },
    {
      "container_type": "Publication",
      "source": "AUTHOR_PUBLICATION_ENTRY",
      "bib": {
        "title": "Kelarutan Nikel Pada Campuran Tanah Berbahan Induk Ultrabasa dengan Gambut pada Kondisi Jenuh dan Tidak Jenuh Air",
        "pub_year": "2023",
        "citation": "Jurnal Ilmu Tanah dan Lingkungan 25 (1), 25-29, 2023"
      },
      "filled": false,
      "author_pub_id": "U4lQjr8AAAAJ:eJXPG6dFmWUC",
      "num_citations": 0
    },
    {
      "container_type": "Publication",
      "source": "AUTHOR_PUBLICATION_ENTRY",
      "bib": {
        "title": "KANGKUNG (Ipomoea reptans) PADA HIDROPONIK WICK SYSTEM The Production and Application of Liquid Organic Fertilizer (LOF) as",
        "pub_year": "2023",
        "citation": "Jurnal Tanah dan Sumberdaya Lahan Vol 10 (2), 401-407, 2023"
      },
      "filled": false,
      "author_pub_id": "U4lQjr8AAAAJ:uLbwQdceFCQC",
      "num_citations": 0
    },
    {
      "container_type": "Publication",
      "source": "AUTHOR_PUBLICATION_ENTRY",
      "bib": {
        "title": "PENGARUH PENAMBAHAN KOMPOS KOTORAN SAPI DAN FLY ASH-BOTTOM ASH (FABA) TERHADAP KARAKTERISTIK KIMIA PADA TANAH BERTEKSTUR PASIR DAN PERTUMBUHAN TOMAT.",
        "pub_year": "2022",
        "citation": "Journal of Soil Science & Environment/Jurnal Ilmu Tanah dan Lingkungan 24 (1), 2022"
      },
      "filled": false,
      "author_pub_id": "U4lQjr8AAAAJ:eflP2zaiRacC",
      "num_citations": 0
    },
    {
      "container_type": "Publication",
      "source": "AUTHOR_PUBLICATION_ENTRY",
      "bib": {
        "title": "Characteristic Observation of Cordyceps Militaris (L) Wild Type Strain from Five Oil Palm Plantation in Muara Wahau East Borneo",
        "pub_year": "2021",
        "citation": "Jurnal Penelitian Kelapa Sawit 29 (3), 167-175, 2021"
      },
      "filled": false,
      "author_pub_id": "U4lQjr8AAAAJ:geHnlv5EZngC",
      "num_citations": 0
    },
    {
      "container_type": "Publication",
      "source": "AUTHOR_PUBLICATION_ENTRY",
      "bib": {
        "title": "Application of Cu and Zn to improve the growth of maize and sorghum in high-pH soils",
        "pub_year": "2021",
        "citation": "IOP Conference Series: Earth and Environmental Science 694 (1), 012054, 2021"
      },
      "filled": false,
      "author_pub_id": "U4lQjr8AAAAJ:CHSYGLWDkRkC",
      "num_citations": 0
    },
    {
      "container_type": "Publication",
      "source": "AUTHOR_PUBLICATION_ENTRY",
      "bib": {
        "title": "Damaged soil vs degraded soil: a brief note on the Government Regulation of Indonesia No. 4/2001",
        "pub_year": "2020",
        "citation": "IOP Conference Series: Earth and Environmental Science 504 (1), 012016, 2020"
      },
      "filled": false,
      "author_pub_id": "U4lQjr8AAAAJ:b0M2c_1WBrUC",
      "num_citations": 0
    },
    {
      "container_type": "Publication",
      "source": "AUTHOR_PUBLICATION_ENTRY",
      "bib": {
        "title": "Identifikasi Status Ketersediaan Boron pada Tanah di Beberapa Daerah di Indonesia.",
        "pub_year": "2020",
        "citation": "IPB University, 2020"
      },
      "filled": false,
      "author_pub_id": "U4lQjr8AAAAJ:PR6Y55bgFSsC",
      "num_citations": 0
    },
    {
      "container_type": "Publication",
      "source": "AUTHOR_PUBLICATION_ENTRY",
      "bib": {
        "title": "Evaluasi Pengaruh Bajak Dalam dan Penambahan Bahan Organik terhadap Sifat Biologi Tanah dan Petumbuhan Akar Kelapa Sawit.",
        "pub_year": "2020",
        "citation": "IPB University, 2020"
      },
      "filled": false,
      "author_pub_id": "U4lQjr8AAAAJ:VL0QpB8kHFEC",
      "num_citations": 0
    },
    {
      "container_type": "Publication",
      "source": "AUTHOR_PUBLICATION_ENTRY",
      "bib": {
        "title": "Evaluasi Pengaruh Bajak Dalam dan Pemberian Bahan Organik terhadap Produksi serta Serapan Hara Tanaman Kelapa Sawit",
        "pub_year": "2019",
        "citation": "Bogor Agricultural University (IPB), 2019"
      },
      "filled": false,
      "author_pub_id": "U4lQjr8AAAAJ:dQ2og3OwTAUC",
      "num_citations": 0
    },
    {
      "container_type": "Publication",
      "source": "AUTHOR_PUBLICATION_ENTRY",
      "bib": {
        "title": "Penelitian terhadap Berbagai Komposisi Media Pembibitan Diuji dengan Menggunakan Tanaman Caisim (Brassica juncea L.).",
        "pub_year": "2019",
        "citation": "Bogor Agriculture University (IPB), 2019"
      },
      "filled": false,
      "author_pub_id": "U4lQjr8AAAAJ:hkOj_22Ku90C",
      "num_citations": 0
    },
    {
      "container_type": "Publication",
      "source": "AUTHOR_PUBLICATION_ENTRY",
      "bib": {
        "title": "Evaluasi Pengaruh Bajak Dalam dan Pemberian Bahan Organik terhadap Karakteristik Sifat Fisik Tanah di Perkebunan Kelapa Sawit.",
        "pub_year": "2019",
        "citation": "Bogor Agricultural University (IPB), 2019"
      },
      "filled": false,
      "author_pub_id": "U4lQjr8AAAAJ:ZuybSZzF8UAC",
      "num_citations": 0
    },
    {
      "container_type": "Publication",
      "source": "AUTHOR_PUBLICATION_ENTRY",
      "bib": {
        "title": "Keanekaragaman Jenis Ikan dan Makanan Beberapa Ikan Ekonomis Penting di Perairan Pantai Kupang, Lubuk Damar, Aceh Tamiang",
        "pub_year": "2019",
        "citation": "Bogor Agricultural University (IPB), 2019"
      },
      "filled": false,
      "author_pub_id": "U4lQjr8AAAAJ:ye4kPcJQO24C",
      "num_citations": 0
    },
    {
      "container_type": "Publication",
      "source": "AUTHOR_PUBLICATION_ENTRY",
      "bib": {
        "title": "Evaluasi Metode Ekstraksi HCl dan Metode Ekstraksi EDTA sebagai Metode Alternatif Analisis Hara pada Tanaman Kelapa Sawit.",
        "pub_year": "2018",
        "citation": "Bogor Agricultural University (IPB), 2018"
      },
      "filled": false,
      "author_pub_id": "U4lQjr8AAAAJ:UHK10RUVsp4C",
      "num_citations": 0
    },
    {
      "container_type": "Publication",
      "source": "AUTHOR_PUBLICATION_ENTRY",
      "bib": {
        "title": "Kajian Sifat Kimia dan Biologi Tanah Sawah Terhadap Hasil Produksi Padi (Oryza sativa L.).",
        "pub_year": "2018",
        "citation": "Bogor Agricultural University (IPB), 2018"
      },
      "filled": false,
      "author_pub_id": "U4lQjr8AAAAJ:1yQoGdGgb4wC",
      "num_citations": 0
    },
    {
      "container_type": "Publication",
      "source": "AUTHOR_PUBLICATION_ENTRY",
      "bib": {
        "title": "Pengaruh Pemberian Kapur dan Fosfat Alam dalam Menetralisir Aluminium terhadap Pertumbuhan Bibit Kelapa Sawit (Elaeis guineensis Jacq.) pada Bahan Tanah Podsolik Jasinga.",
        "pub_year": "2018",
        "citation": "Bogor Agricultural University (IPB), 2018"
      },
      "filled": false,
      "author_pub_id": "U4lQjr8AAAAJ:N5tVd3kTz84C",
      "num_citations": 0
    },
    {
      "container_type": "Publication",
      "source": "AUTHOR_PUBLICATION_ENTRY",
      "bib": {
        "title": "Dinamika populasi Collembola pada tanaman kelapa sawit di perkebunan Cikasungka Kabupaten Bogor",
        "pub_year": "2017",
        "citation": ""
      },
      "filled": false,
      "author_pub_id": "U4lQjr8AAAAJ:BrmTIyaxlBUC",
      "num_citations": 0
    },
    {
      "container_type": "Publication",
      "source": "AUTHOR_PUBLICATION_ENTRY",
      "bib": {
        "title": "Pengaruh Pemberian Bahan Humat terhadap Pertumbuhan Tanaman Jagung (Zea mays) pada Tanah Latosol Darmaga dan Podsolik Jasinga",
        "pub_year": "2015",
        "citation": ""
      },
      "filled": false,
      "author_pub_id": "U4lQjr8AAAAJ:RGFaLdJalmkC",
      "num_citations": 0
    },
    {
      "container_type": "Publication",
      "source": "AUTHOR_PUBLICATION_ENTRY",
      "bib": {
        "title": "SIFAT-SIFAT TANAH DAN KONSENTRASI HERBISIDA GLIFOSAT PADA BEBERAPA KEDALAMAN DAN WAKTU SETELAH APLIKASI PADA TANAH LATOSOL DARI DARMAGA, BOGOR",
        "pub_year": "2014",
        "citation": ""
      },
      "filled": false,
      "author_pub_id": "U4lQjr8AAAAJ:KxtntwgDAa4C",
      "num_citations": 0
    },
    {
      "container_type": "Publication",
      "source": "AUTHOR_PUBLICATION_ENTRY",
      "bib": {
        "title": "Renovation Of Acid Sulfate Soil For Integrated Farming At Delta Berbak, Jambi Province",
        "pub_year": "2013",
        "citation": "IPB (Bogor Agricultural University), 2013"
      },
      "filled": false,
      "author_pub_id": "U4lQjr8AAAAJ:_B80troHkn4C",
      "num_citations": 0
    },
    {
      "container_type": "Publication",
      "source": "AUTHOR_PUBLICATION_ENTRY",
      "bib": {
        "title": "PENGARUH PENCUCIAN, APLIKASI GLIRISIDIA DAN UREA SERTA KOMBINASINYA TERHADAP KESELARASAN PENYEDIAAN NITROGEN DENGAN PERTUMBUHAN JAGUNG PADA INCEPTISOL DARMAGA",
        "pub_year": "2013",
        "citation": ""
      },
      "filled": false,
      "author_pub_id": "U4lQjr8AAAAJ:Y5dfb0dijaUC",
      "num_citations": 0
    },
    {
      "container_type": "Publication",
      "source": "AUTHOR_PUBLICATION_ENTRY",
      "bib": {
        "title": "Manajemen dan Teknik Pengelolaan Sampah Pasar DKI Jakarta",
        "pub_year": "2013",
        "citation": ""
      },
      "filled": false,
      "author_pub_id": "U4lQjr8AAAAJ:eMMeJKvmdy0C",
      "num_citations": 0
    },
    {
      "container_type": "Publication",
      "source": "AUTHOR_PUBLICATION_ENTRY",
      "bib": {
        "title": "Utilization of acid sulfate soil in rantau rasau-jambi province for cultivation of gaharu (Aquilaria sp)",
        "pub_year": "2013",
        "citation": ""
      },
      "filled": false,
      "author_pub_id": "U4lQjr8AAAAJ:Mojj43d5GZwC",
      "num_citations": 0
    },
    {
      "container_type": "Publication",
      "source": "AUTHOR_PUBLICATION_ENTRY",
      "bib": {
        "title": "SOME EFFORTS FOR IMPROVING DEGRADED PEATLAND IN THE BERBAK DELTA, JAMBI, INDONESIA",
        "pub_year": "2013",
        "citation": ""
      },
      "filled": false,
      "author_pub_id": "U4lQjr8AAAAJ:bnK-pcrLprsC",
      "num_citations": 0
    },
    {
      "container_type": "Publication",
      "source": "AUTHOR_PUBLICATION_ENTRY",
      "bib": {
        "title": "Kondisi TPA Bantar Gebang Saat Ini",
        "pub_year": "2013",
        "citation": ""
      },
      "filled": false,
      "author_pub_id": "U4lQjr8AAAAJ:5ugPr518TE4C",
      "num_citations": 0
    },
    {
      "container_type": "Publication",
      "source": "AUTHOR_PUBLICATION_ENTRY",
      "bib": {
        "title": "Characterization and Resilience of Upland Degraded Soils of Central Kalimantan",
        "pub_year": "2012",
        "citation": "Indonesian Soil and Climate Journal, 132409, 2012"
      },
      "filled": false,
      "author_pub_id": "U4lQjr8AAAAJ:R3hNpaxXUhUC",
      "num_citations": 0
    },
    {
      "container_type": "Publication",
      "source": "AUTHOR_PUBLICATION_ENTRY",
      "bib": {
        "title": "Changes of Soil Organic Matter Fraction on Ultisols Jasinga by Soil Tillage and Organic Matter Practices",
        "pub_year": "2012",
        "citation": "Indonesian Soil and Climate Journal, 133708, 2012"
      },
      "filled": false,
      "author_pub_id": "U4lQjr8AAAAJ:5nxA0vEk-isC",
      "num_citations": 0
    },
    {
      "container_type": "Publication",
      "source": "AUTHOR_PUBLICATION_ENTRY",
      "bib": {
        "title": "Nutrient cycle in acacia crassicarpa plantation on deep tropical peatland at Bukitbatu, Bengkalis, Indonesia",
        "pub_year": "2011",
        "citation": "Audit Visual Unit, Department of Agriculture Peradeniya, Sri Lanka, 2011"
      },
      "filled": false,
      "author_pub_id": "U4lQjr8AAAAJ:l7t_Zn2s7bgC",
      "num_citations": 0
    },
    {
      "container_type": "Publication",
      "source": "AUTHOR_PUBLICATION_ENTRY",
      "bib": {
        "title": "Kajian Perbaikan Teknologi Budidaya Cacing Tanah Eisenia Foetida Savigny untuk Meningkatkan Produksi Biomassa dan Kualitas Eksmecat Dengan Memanfaatkan Limbah Organik Sebagai Media",
        "pub_year": "2010",
        "citation": "IPB (Bogor Agricultural University), 2010"
      },
      "filled": false,
      "author_pub_id": "U4lQjr8AAAAJ:WA5NYHcadZ8C",
      "num_citations": 0
    },
    {
      "container_type": "Publication",
      "source": "AUTHOR_PUBLICATION_ENTRY",
      "bib": {
        "title": "Populasi mikroba dan fluks metana (CH4) serta nitrous oksida (N2O) pada tanah sawah: pengaruh pengelolaan air, bahan organik, dan pupuk nitrogen",
        "pub_year": "2010",
        "citation": "IPB (Bogor Agricultural University), 2010"
      },
      "filled": false,
      "author_pub_id": "U4lQjr8AAAAJ:t6usbXjVLHcC",
      "num_citations": 0
    },
    {
      "container_type": "Publication",
      "source": "AUTHOR_PUBLICATION_ENTRY",
      "bib": {
        "title": "Utilization of Acid Sulfate Soil in Rantau Rasau-Jambi Province for Cultivation of Gaharu (Aquailaria sp)",
        "pub_year": "2009",
        "citation": ""
      },
      "filled": false,
      "author_pub_id": "U4lQjr8AAAAJ:ns9cj8rnVeAC",
      "num_citations": 0
    },
    {
      "container_type": "Publication",
      "source": "AUTHOR_PUBLICATION_ENTRY",
      "bib": {
        "title": "Absorption capability of HDTMA-activated bentonite on organic and inorganic pollutant in some industrial liquid waste",
        "pub_year": "2008",
        "citation": ""
      },
      "filled": false,
      "author_pub_id": "U4lQjr8AAAAJ:vRqMK49ujn8C",
      "num_citations": 0
    },
    {
      "container_type": "Publication",
      "source": "AUTHOR_PUBLICATION_ENTRY",
      "bib": {
        "title": "Some Efforts for Improving Degraded Peatland in Berbak Delta-Jambi, Indonesia",
        "pub_year": "2007",
        "citation": "International Seminar Tropical Peat Seminar. Yogyakarta, 27-29, 2007"
      },
      "filled": false,
      "author_pub_id": "U4lQjr8AAAAJ:fPk4N6BV_jEC",
      "num_citations": 0
    },
    {
      "container_type": "Publication",
      "source": "AUTHOR_PUBLICATION_ENTRY",
      "bib": {
        "title": "Study of soil macro fauna on different crop land types in andisol Pasir Sarongge, west Java",
        "pub_year": "2006",
        "citation": "Tropics 15 (4), 355-363, 2006"
      },
      "filled": false,
      "author_pub_id": "U4lQjr8AAAAJ:r0BpntZqJG4C",
      "num_citations": 0
    },
    {
      "container_type": "Publication",
      "source": "AUTHOR_PUBLICATION_ENTRY",
      "bib": {
        "title": "Fluks Metana dan Karakteristik Tanah pada Beberapa Macam Sistem Budidaya",
        "pub_year": "2006",
        "citation": "Indonesian Journal of Agronomy 34 (3), 2006"
      },
      "filled": false,
      "author_pub_id": "U4lQjr8AAAAJ:HDshCWvjkbEC",
      "num_citations": 0
    },
    {
      "container_type": "Publication",
      "source": "AUTHOR_PUBLICATION_ENTRY",
      "bib": {
        "title": "loomd/0/iiidDtI/nJ'irODlHfDI",
        "pub_year": "2005",
        "citation": "Jurnal Tanah dan Lingkungan 7 (2), 54-57, 2005"
      },
      "filled": false,
      "author_pub_id": "U4lQjr8AAAAJ:ufrVoPGSRksC",
      "num_citations": 0
    },
    {
      "container_type": "Publication",
      "source": "AUTHOR_PUBLICATION_ENTRY",
      "bib": {
        "title": "Pengalaman Penanaman 7000 Batang Tanaman Gaharu Pada Lahan Sulfat Masam di Rantau Rasau, Jambi",
        "pub_year": "2005",
        "citation": ""
      },
      "filled": false,
      "author_pub_id": "U4lQjr8AAAAJ:738O_yMBCRsC",
      "num_citations": 0
    },
    {
      "container_type": "Publication",
      "source": "AUTHOR_PUBLICATION_ENTRY",
      "bib": {
        "title": "Direct and Indirect Methods of Soil Microbial-Biomass Determination: Weakness and Srength",
        "pub_year": "2003",
        "citation": "IPB (Bogor Agricultural University), 2003"
      },
      "filled": false,
      "author_pub_id": "U4lQjr8AAAAJ:tS2w5q8j5-wC",
      "num_citations": 0
    },
    {
      "container_type": "Publication",
      "source": "AUTHOR_PUBLICATION_ENTRY",
      "bib": {
        "title": "Drainage system model in relation with pyrite oxidation and its effect on soil chemicophysical properties and water quality on acid sulphate soil",
        "pub_year": "2003",
        "citation": ""
      },
      "filled": false,
      "author_pub_id": "U4lQjr8AAAAJ:qxL8FJ1GzNcC",
      "num_citations": 0
    },
    {
      "container_type": "Publication",
      "source": "AUTHOR_PUBLICATION_ENTRY",
      "bib": {
        "title": "Nitrogen fixation microbes and phosphate solubilizing from Rhizopus oryzae and on peat soil of One Million Hectare Peat Soil Project in Central Kalimantan (Indonesia)",
        "pub_year": "1999",
        "citation": "Seminar Pertemuan Ilmiah Tahunan Perhimpunan Mikrobiologi Indonesia, Bandar \u2026, 1999"
      },
      "filled": false,
      "author_pub_id": "U4lQjr8AAAAJ:Y0pCki6q_DkC",
      "num_citations": 0
    },
    {
      "container_type": "Publication",
      "source": "AUTHOR_PUBLICATION_ENTRY",
      "bib": {
        "title": "Effect of cow manure and oil on the population and activity of soil microorganism on garden soil, rubbish soil and grassland soil",
        "pub_year": "1999",
        "citation": "Jurnal Agroland (Indonesia), 1999"
      },
      "filled": false,
      "author_pub_id": "U4lQjr8AAAAJ:d1gkVwhDpl0C",
      "num_citations": 0
    },
    {
      "container_type": "Publication",
      "source": "AUTHOR_PUBLICATION_ENTRY",
      "bib": {
        "title": "Measuring of ergosterol in soils",
        "pub_year": "1993",
        "citation": "Mitteilungen der Deutschen Bodenkundlichen Gesellschaft (Germany), 1993"
      },
      "filled": false,
      "author_pub_id": "U4lQjr8AAAAJ:hqOjcs7Dif8C",
      "num_citations": 0
    },
    {
      "container_type": "Publication",
      "source": "AUTHOR_PUBLICATION_ENTRY",
      "bib": {
        "title": "Studi potensi dan perkembangan teknologi produksi biogas serta aplikasi pemanfaatannya",
        "citation": "IPB University, 0"
      },
      "filled": false,
      "author_pub_id": "U4lQjr8AAAAJ:Fu2w8maKXqMC",
      "num_citations": 0
    },
    {
      "container_type": "Publication",
      "source": "AUTHOR_PUBLICATION_ENTRY",
      "bib": {
        "title": "Keefisiensi nitrogen dari azolla pinnata dan urea pada tanaman padi varietas IR-36 terhadap serapan berbagai unsur hara",
        "citation": "IPB University, 0"
      },
      "filled": false,
      "author_pub_id": "U4lQjr8AAAAJ:W5xh706n7nkC",
      "num_citations": 0
    },
    {
      "container_type": "Publication",
      "source": "AUTHOR_PUBLICATION_ENTRY",
      "bib": {
        "title": "Biodiversitas makrobiota tanah di berbagai tipe penggunaan lahan pada andisol Pasir Sarongge",
        "citation": "IPB University, 0"
      },
      "filled": false,
      "author_pub_id": "U4lQjr8AAAAJ:_Ybze24A_UAC",
      "num_citations": 0
    },
    {
      "container_type": "Publication",
      "source": "AUTHOR_PUBLICATION_ENTRY",
      "bib": {
        "title": "Dinamika Populasi Dan Keanekaragaman Collembola Pada Tanaman Kelapa Sawit Di Perkebunan Cikasungka Kabupaten Bogor",
        "citation": "IPB (Bogor Agricultural University), 0"
      },
      "filled": false,
      "author_pub_id": "U4lQjr8AAAAJ:JoZmwDi-zQgC",
      "num_citations": 0
    },
    {
      "container_type": "Publication",
      "source": "AUTHOR_PUBLICATION_ENTRY",
      "bib": {
        "title": "Improvement of acid soil productivity: The use of shrimp-tile pump in rice cultivation during dry season",
        "citation": ""
      },
      "filled": false,
      "author_pub_id": "U4lQjr8AAAAJ:tkaPQYYpVKoC",
      "num_citations": 0
    },
    {
      "container_type": "Publication",
      "source": "AUTHOR_PUBLICATION_ENTRY",
      "bib": {
        "title": "Proceeding Of Bogor Symposium And Workshop On Tropical Peatland Management\" Wise Use Of Tropical Peatlend\"",
        "citation": "IPB (Bogor Agricultural University), 0"
      },
      "filled": false,
      "author_pub_id": "U4lQjr8AAAAJ:AXPGKjj_ei8C",
      "num_citations": 0
    },
    {
      "container_type": "Publication",
      "source": "AUTHOR_PUBLICATION_ENTRY",
      "bib": {
        "title": "Reklamasi Lahan Bekas Tambang Pasir Besi Melalui Teknik Ameliorasi In Situ Bahan Organik",
        "citation": "IPB (Bogor Agricultural University), 0"
      },
      "filled": false,
      "author_pub_id": "U4lQjr8AAAAJ:HE397vMXCloC",
      "num_citations": 0
    },
    {
      "container_type": "Publication",
      "source": "AUTHOR_PUBLICATION_ENTRY",
      "bib": {
        "title": "Pengaruh Penggunaan berbagai Pupuk Daun terhadap Pertumbuhan Caisim (Brassica juncea L)",
        "citation": ""
      },
      "filled": false,
      "author_pub_id": "U4lQjr8AAAAJ:olpn-zPbct0C",
      "num_citations": 0
    },
    {
      "container_type": "Publication",
      "source": "AUTHOR_PUBLICATION_ENTRY",
      "bib": {
        "title": "Kandungan ergosterol bebas tanah pada beberapa tipe penggunaan lahan di kebun percobaan Cikabayan, Dramaga",
        "citation": "IPB (Bogor Agricultural University), 0"
      },
      "filled": false,
      "author_pub_id": "U4lQjr8AAAAJ:wbdj-CoPYUoC",
      "num_citations": 0
    },
    {
      "container_type": "Publication",
      "source": "AUTHOR_PUBLICATION_ENTRY",
      "bib": {
        "title": "Pemanfaatan cacing tanah (Pheretima hupiensis) untuk meningkatkan produktivitas ultisol lahan kering",
        "citation": "IPB (Bogor Agricultural University), 0"
      },
      "filled": false,
      "author_pub_id": "U4lQjr8AAAAJ:J-pR_7NvFogC",
      "num_citations": 0
    },
    {
      "container_type": "Publication",
      "source": "AUTHOR_PUBLICATION_ENTRY",
      "bib": {
        "title": "Kelimpahan Dan Keanekaragaman Collembola Pada Empat Penggunaan Lahan Di Lanskap Hutan Harapan Jambi",
        "citation": "Bogor Agricultural University (IPB), 0"
      },
      "filled": false,
      "author_pub_id": "U4lQjr8AAAAJ:V3AGJWp-ZtQC",
      "num_citations": 0
    },
    {
      "container_type": "Publication",
      "source": "AUTHOR_PUBLICATION_ENTRY",
      "bib": {
        "title": "Absorption capability of HDTMA-activated bentonite on organic and inorganic pollutant in some industrial liquid waste",
        "citation": ""
      },
      "filled": false,
      "author_pub_id": "U4lQjr8AAAAJ:D03iK_w7-QYC",
      "num_citations": 0
    },
    {
      "container_type": "Publication",
      "source": "AUTHOR_PUBLICATION_ENTRY",
      "bib": {
        "title": "CONTRIBUTION FROM ROOT RESPIRATION AND LITTER DECOMPOSITION TO CARBON FLUX IN TROPICAL PEATLAND",
        "citation": ""
      },
      "filled": false,
      "author_pub_id": "U4lQjr8AAAAJ:GnPB-g6toBAC",
      "num_citations": 0
    },
    {
      "container_type": "Publication",
      "source": "AUTHOR_PUBLICATION_ENTRY",
      "bib": {
        "title": "Use of Earthworm to Increase Upland Ultisols Productivity",
        "citation": "Indonesian Soil and Climate Journal, 133873, 0"
      },
      "filled": false,
      "author_pub_id": "U4lQjr8AAAAJ:TFP_iSt0sucC",
      "num_citations": 0
    },
    {
      "container_type": "Publication",
      "source": "AUTHOR_PUBLICATION_ENTRY",
      "bib": {
        "title": "The availability of fertilizer-P applied of sitiung soli of west sumatra after few weeks of lime applications",
        "citation": ""
      },
      "filled": false,
      "author_pub_id": "U4lQjr8AAAAJ:ULOm3_A8WrAC",
      "num_citations": 0
    },
    {
      "container_type": "Publication",
      "source": "AUTHOR_PUBLICATION_ENTRY",
      "bib": {
        "title": "Isolasi dan Seleksi Galur Bradyrhizobium japonicum Asal Tanah Gambut Isolation and Selection of Bradyrhizobium japonicum Isolated from Peat Soils",
        "citation": ""
      },
      "filled": false,
      "author_pub_id": "U4lQjr8AAAAJ:Se3iqnhoufwC",
      "num_citations": 0
    }
  ],
  "public_access": {
    "available": 1,
    "not_available": 0
  }
}