{
  "container_type": "Author",
  "filled": [
    "basics",
    "indices",
    "counts",
    "coauthors",
    "publications",
    "public_access"
  ],
  "scholar_id": "KVEm12EAAAAJ",
  "source": "AUTHOR_PROFILE_PAGE",
  "name": "Retno Lestari",
  "url_picture": "https://scholar.googleusercontent.com/citations?view_op=view_photo&user=KVEm12EAAAAJ&citpid=1",
  "affiliation": "Universitas Indonesia",
  "organization": 6271598661313830606,
  "interests": [
    "Biology",
    "Biotechnology",
    "Genetics",
    "Immunology"
  ],
  "email_domain": "@ui.ac.id",
  "homepage": "http://staff.ui.ac.id/retno.lestari",
  "citedby": 146,
  "citedby5y": 105,
  "hindex": 5,
  "hindex5y": 4,
  "i10index": 5,
  "i10index5y": 4,
  "cites_per_year": {
    "2009": 1,
    "2010": 1,
    "2011": 3,
    "2012": 1,
    "2013": 1,
    "2014": 1,
    "2015": 3,
    "2016": 3,
    "2017": 8,
    "2018": 18,
    "2019": 14,
    "2020": 23,
    "2021": 31,
    "2022": 17,
    "2023": 17,
    "2024": 3
  },
  "coauthors": [],
  "publications": [
    {
      "container_type": "Publication",
      "source": "AUTHOR_PUBLICATION_ENTRY",
      "bib": {
        "title": "Overexpression of Hevea brasiliensis ethylene response factor HbERF\u2010IXc5 enhances growth and tolerance to abiotic stress and affects laticifer differentiation",
        "pub_year": "2018",
        "citation": "Plant biotechnology journal 16 (1), 322-336, 2018"
      },
      "filled": false,
      "author_pub_id": "KVEm12EAAAAJ:ufrVoPGSRksC",
      "num_citations": 51,
      "citedby_url": "https://scholar.google.com/scholar?oi=bibs&hl=en&cites=16948346728966449001",
      "cites_id": [
        "16948346728966449001"
      ]
    },
    {
      "container_type": "Publication",
      "source": "AUTHOR_PUBLICATION_ENTRY",
      "bib": {
        "title": "The effect of sucrose on sperm quality of Osphronemus goramy two days post-cryopreservation",
        "pub_year": "2012",
        "citation": "Journal of Agricultural Science and Technology. B 2 (2B), 204, 2012"
      },
      "filled": false,
      "author_pub_id": "KVEm12EAAAAJ:u-x6o8ySG0sC",
      "num_citations": 27,
      "citedby_url": "https://scholar.google.com/scholar?oi=bibs&hl=en&cites=5080433854512214609,13496922680679969562",
      "cites_id": [
        "5080433854512214609",
        "13496922680679969562"
      ]
    },
    {
      "container_type": "Publication",
      "source": "AUTHOR_PUBLICATION_ENTRY",
      "bib": {
        "title": "The effect of skim milk combined with 5% of methanol on motiliy, viability, and abnormality of Java barb, Barbonymus gonionotus spermatozoa after 24 hours freezing.",
        "pub_year": "2016",
        "citation": ""
      },
      "filled": false,
      "author_pub_id": "KVEm12EAAAAJ:UeHWp8X0CEIC",
      "num_citations": 23,
      "citedby_url": "https://scholar.google.com/scholar?oi=bibs&hl=en&cites=8946796216902062504",
      "cites_id": [
        "8946796216902062504"
      ]
    },
    {
      "container_type": "Publication",
      "source": "AUTHOR_PUBLICATION_ENTRY",
      "bib": {
        "title": "Sperm motility of giant gourami (Osphronemus goramy, Lacepede, 1801) at several concentrations of honey combined with DMSO after short-term storage",
        "pub_year": "2017",
        "citation": "Aquaculture, Aquarium, Conservation & Legislation 10 (2), 156-163, 2017"
      },
      "filled": false,
      "author_pub_id": "KVEm12EAAAAJ:WF5omc3nYNoC",
      "num_citations": 22,
      "citedby_url": "https://scholar.google.com/scholar?oi=bibs&hl=en&cites=1424581528397770214",
      "cites_id": [
        "1424581528397770214"
      ]
    },
    {
      "container_type": "Publication",
      "source": "AUTHOR_PUBLICATION_ENTRY",
      "bib": {
        "title": "Efek estrogenik ekstrak etanol 70% kunyit (Curcuma domestica Val.) terhadap mencit (Mus musculus L.) betina yang diovariektomi",
        "pub_year": "2010",
        "citation": "Makara journal of Science 11 (2), 21, 2010"
      },
      "filled": false,
      "author_pub_id": "KVEm12EAAAAJ:zYLM7Y9cAGgC",
      "num_citations": 11,
      "citedby_url": "https://scholar.google.com/scholar?oi=bibs&hl=en&cites=15370702317027828238",
      "cites_id": [
        "15370702317027828238"
      ]
    },
    {
      "container_type": "Publication",
      "source": "AUTHOR_PUBLICATION_ENTRY",
      "bib": {
        "title": "The effect of glucose in various concentrations on sperm quality of Barbonymus gonionotus (Bleeker, 1850) 24 hours postcryopreservation",
        "pub_year": "2009",
        "citation": "The Journal of Reproduction and Development Supplement The 102nd Meeting of \u2026, 2009"
      },
      "filled": false,
      "author_pub_id": "KVEm12EAAAAJ:d1gkVwhDpl0C",
      "num_citations": 5,
      "citedby_url": "https://scholar.google.com/scholar?oi=bibs&hl=en&cites=1303863434346372759",
      "cites_id": [
        "1303863434346372759"
      ]
    },
    {
      "container_type": "Publication",
      "source": "AUTHOR_PUBLICATION_ENTRY",
      "bib": {
        "title": "The Intracellular Cryoprotectant Effects in Preserving Goramy Spermatozoa after Two Days Sub-Zero Freezing",
        "pub_year": "2015",
        "citation": "Aquacultura Indonesiana 16 (1), 16-21, 2015"
      },
      "filled": false,
      "author_pub_id": "KVEm12EAAAAJ:IjCSPb-OGe4C",
      "num_citations": 4,
      "citedby_url": "https://scholar.google.com/scholar?oi=bibs&hl=en&cites=16446386538789232074",
      "cites_id": [
        "16446386538789232074"
      ]
    },
    {
      "container_type": "Publication",
      "source": "AUTHOR_PUBLICATION_ENTRY",
      "bib": {
        "title": "Peranan Dimetil Sulfoksida sebagai Krioprotektan dalam Mempertahankan Kualitas Spermatozoa Ikan Gurami, Osphronemus goramy Lacepede, 1801, Dua Puluh Empat Jam Pascakriopreservasi",
        "pub_year": "2011",
        "citation": "Biota: Jurnal Ilmiah Ilmu-Ilmu Hayati, 10-15, 2011"
      },
      "filled": false,
      "author_pub_id": "KVEm12EAAAAJ:2osOgNQ5qMEC",
      "num_citations": 2,
      "citedby_url": "https://scholar.google.com/scholar?oi=bibs&hl=en&cites=8370819399698031499",
      "cites_id": [
        "8370819399698031499"
      ]
    },
    {
      "container_type": "Publication",
      "source": "AUTHOR_PUBLICATION_ENTRY",
      "bib": {
        "title": "Establishment of Hevea brasiliensis lines overexpressing genes involved in ethylene signalling pathway",
        "pub_year": "2016",
        "citation": "Menara Perkebunan 84 (1), 2016"
      },
      "filled": false,
      "author_pub_id": "KVEm12EAAAAJ:Tyk-4Ss8FVUC",
      "num_citations": 1,
      "citedby_url": "https://scholar.google.com/scholar?oi=bibs&hl=en&cites=1897245133030000030",
      "cites_id": [
        "1897245133030000030"
      ]
    },
    {
      "container_type": "Publication",
      "source": "AUTHOR_PUBLICATION_ENTRY",
      "bib": {
        "title": "Mutational analysis of exon 4 of the 6-pyruvoyl-tetrahydropterin synthase gene in an Indonesian population",
        "pub_year": "2018",
        "citation": "Journal of Physics: Conference Series 1073 (3), 032072, 2018"
      },
      "filled": false,
      "author_pub_id": "KVEm12EAAAAJ:LkGwnXOMwfcC",
      "num_citations": 0
    },
    {
      "container_type": "Publication",
      "source": "AUTHOR_PUBLICATION_ENTRY",
      "bib": {
        "title": "Functional analysis in Hevea brasiliensis of the HbERF-IXc4 and HbERF-IXc5 genes, two potential orthologs Arabidopsis ERF1 gene",
        "pub_year": "2016",
        "citation": "Montpellier SupAgro; Graduate School of the Bogor Agricultural University \u2026, 2016"
      },
      "filled": false,
      "author_pub_id": "KVEm12EAAAAJ:_FxGoFyzp5QC",
      "num_citations": 0
    },
    {
      "container_type": "Publication",
      "source": "AUTHOR_PUBLICATION_ENTRY",
      "bib": {
        "title": "Juvenile Hevea transgenic plants over-expressing transcription factor HbERF-IXc5 develop more latex cells than wild-type material",
        "pub_year": "2016",
        "citation": "CRRI, 2016"
      },
      "filled": false,
      "author_pub_id": "KVEm12EAAAAJ:Y0pCki6q_DkC",
      "num_citations": 0
    },
    {
      "container_type": "Publication",
      "source": "AUTHOR_PUBLICATION_ENTRY",
      "bib": {
        "title": "THE COMBINATION EFFECT OF 5% OF METHANOL AND SKIM MILK ON SPERMATOZOA QUALITY OF JAVA BARB (Barbonymus gonionotus) 24 HOURS AFTER SUB-ZERO FREEZING",
        "pub_year": "2015",
        "citation": "\ud55c\uad6d\uc218\uc0b0\uacfc\ud559\ud68c \uc591\uc2dd\ubd84\uacfc \ud559\uc220\ub300\ud68c, 8-8, 2015"
      },
      "filled": false,
      "author_pub_id": "KVEm12EAAAAJ:9yKSN-GCB0IC",
      "num_citations": 0
    },
    {
      "container_type": "Publication",
      "source": "AUTHOR_PUBLICATION_ENTRY",
      "bib": {
        "title": "Production of Hevea brasiliensis transgenic lines overexpressing transcription factors involved in ethylene signalling pathway",
        "pub_year": "2015",
        "citation": "Prince of Songkla University, 2015"
      },
      "filled": false,
      "author_pub_id": "KVEm12EAAAAJ:W7OEmFMy1HYC",
      "num_citations": 0
    },
    {
      "container_type": "Publication",
      "source": "AUTHOR_PUBLICATION_ENTRY",
      "bib": {
        "title": "Identification of signalling factors involved in the regulation of laticifer metabolism by tapping and Ethephon stimulation in Hevea brasiliensis",
        "pub_year": "2014",
        "citation": ""
      },
      "filled": false,
      "author_pub_id": "KVEm12EAAAAJ:YsMSGLbcyi4C",
      "num_citations": 0
    }
  ],
  "public_access": {
    "available": 0,
    "not_available": 0
  }
}